tlbo_optimization/__init__.py
tlbo_optimization/tlbo_optimization.py
tlbo_optimization-0.1.0.dist-info/AUTHORS.rst
tlbo_optimization-0.1.0.dist-info/LICENSE
tlbo_optimization-0.1.0.dist-info/METADATA
tlbo_optimization-0.1.0.dist-info/WHEEL
tlbo_optimization-0.1.0.dist-info/top_level.txt
tlbo_optimization-0.1.0.dist-info/RECORD
