Metadata-Version: 2.1
Name: tlbo_optimization
Version: 0.1.0
Summary: Teaching-Learning-Based Optimization (TLBO) algorithm
Author-email: mohamad bagher davoodi <mohamadbagherdavoodi@gmail.com>
Maintainer-email: mohamad bagher davoodi <mohamadbagherdavoodi@gmail.com>
License: GNU General Public License v3
Project-URL: bugs, https://github.com/smbd1368/tlbo_optimization/issues
Project-URL: changelog, https://github.com/smbd1368/tlbo_optimization/blob/master/changelog.md
Project-URL: homepage, https://github.com/smbd1368/tlbo_optimization
License-File: LICENSE
License-File: AUTHORS.rst
Provides-Extra: dev
Requires-Dist: coverage ; extra == 'dev'
Requires-Dist: mypy ; extra == 'dev'
Requires-Dist: pytest ; extra == 'dev'
Requires-Dist: ruff ; extra == 'dev'
